django_templateselector-0.2.5.dist-info/DESCRIPTION.rst
django_templateselector-0.2.5.dist-info/LICENSE.txt
django_templateselector-0.2.5.dist-info/METADATA
django_templateselector-0.2.5.dist-info/RECORD
django_templateselector-0.2.5.dist-info/WHEEL
django_templateselector-0.2.5.dist-info/metadata.json
django_templateselector-0.2.5.dist-info/top_level.txt
templateselector/__init__.py
templateselector/admin.py
templateselector/fields.py
templateselector/handlers.py
templateselector/widgets.py
templateselector/static/templateselector/admin_widget.css
templateselector/static/templateselector/fallback.png
templateselector/static/templateselector/widget.css
templateselector/templates/django/forms/widgets/template_selector.html
templateselector/templates/django/forms/widgets/template_selector_option.html
templateselector/tests/__init__.py
templateselector/tests/admin.py
templateselector/tests/models.py
templateselector/tests/test_form_field.py
templateselector/tests/test_model_field.py
templateselector/tests/migrations/0001_initial.py
templateselector/tests/migrations/__init__.py
