Metadata-Version: 2.0
Name: django-templateselector
Version: 0.2.5
Summary: Provides a model field and form field for allowing users to select a template file
Home-page: https://github.com/kezabelle/django-template-selector
Author: Keryn Knight
Author-email: django-templateselector@kerynknight.com
License: BSD License
Keywords: django templateselector widget model form field
Platform: UNKNOWN
Classifier: Development Status :: 3 - Alpha
Classifier: Intended Audience :: Developers
Classifier: License :: OSI Approved :: BSD License
Classifier: Natural Language :: English
Classifier: Programming Language :: Python :: 2
Classifier: Programming Language :: Python :: 2.7
Classifier: Programming Language :: Python :: 3
Classifier: Programming Language :: Python :: 3.5
Classifier: Framework :: Django
Classifier: Framework :: Django :: 1.11
Requires-Dist: Django (>=1.8)
Requires-Dist: scandir (>=1.5); python_version<'3'
